fremko/__init__.py
fremko/__main__.py
fremko/portal.py
fremko/agent/__init__.py
fremko/agent/codeact/__init__.py
fremko/agent/codeact/codeact_agent.py
fremko/agent/codeact/events.py
fremko/agent/codeact/prompts.py
fremko/agent/common/default.py
fremko/agent/common/events.py
fremko/agent/context/__init__.py
fremko/agent/context/agent_persona.py
fremko/agent/context/context_injection_manager.py
fremko/agent/context/episodic_memory.py
fremko/agent/context/reflection.py
fremko/agent/context/task_manager.py
fremko/agent/context/personas/__init__.py
fremko/agent/context/personas/default.py
fremko/agent/context/personas/future_default.py
fremko/agent/droid/__init__.py
fremko/agent/droid/droid_agent.py
fremko/agent/droid/events.py
fremko/agent/oneflows/reflector.py
fremko/agent/planner/__init__.py
fremko/agent/planner/events.py
fremko/agent/planner/planner_agent.py
fremko/agent/planner/prompts.py
fremko/agent/utils/__init__.py
fremko/agent/utils/async_utils.py
fremko/agent/utils/chat_utils.py
fremko/agent/utils/executer.py
fremko/agent/utils/llm_picker.py
fremko/agent/utils/phoenix.py
fremko/cli/__init__.py
fremko/cli/logs.py
fremko/cli/main.py
fremko/tools/__init__.py
fremko/tools/tools.py
fremko/tools/ws.py
fremko/tools/wsdevice.py
fremko/web/app.py
fremko/web/executor.py
fremko/web/static/css/executor.css
fremko/web/static/css/styles.css
fremko/web/static/js/app.js
fremko/web/static/js/executor.js
fremko/web/templates/executor.html
fremko/web/templates/index.html
fremko/ws/__init__.py
fremko/ws/client.py
fremko/ws/server.py
fremko-0.1.5.dist-info/METADATA
fremko-0.1.5.dist-info/WHEEL
fremko-0.1.5.dist-info/entry_points.txt
fremko-0.1.5.dist-info/licenses/LICENSE
fremko-0.1.5.dist-info/RECORD
