Metadata-Version: 2.4
Name: fremko
Version: 0.1.5
Summary: A framework for controlling Android devices through LLM agents
Project-URL: Homepage, https://github.com/johnmalek312/fremko
Project-URL: Bug Tracker, https://github.com/johnmalek312/fremko/issues
Author: johnmalek312
License: MIT
License-File: LICENSE
Classifier: Development Status :: 4 - Beta
Classifier: Intended Audience :: Developers
Classifier: Intended Audience :: Information Technology
Classifier: Intended Audience :: Science/Research
Classifier: License :: OSI Approved :: MIT License
Classifier: Programming Language :: Python :: 3
Classifier: Programming Language :: Python :: 3.10
Classifier: Programming Language :: Python :: 3.11
Classifier: Topic :: Communications :: Chat
Classifier: Topic :: Scientific/Engineering :: Artificial Intelligence
Classifier: Topic :: Software Development :: Libraries :: Application Frameworks
Classifier: Topic :: Software Development :: Libraries :: Python Modules
Classifier: Topic :: Software Development :: Quality Assurance
Classifier: Topic :: Software Development :: Testing
Classifier: Topic :: Software Development :: Testing :: Acceptance
Classifier: Topic :: System :: Emulators
Classifier: Topic :: Utilities
Requires-Python: >=3.10
Requires-Dist: adbutils==2.9.3
Requires-Dist: aiofiles>=23.0.0
Requires-Dist: anthropic>=0.7.0
Requires-Dist: apkutils==2.0.0
Requires-Dist: arize-phoenix>=11.24.1
Requires-Dist: av>=15.0.0
Requires-Dist: click>=8.1.0
Requires-Dist: fastapi>=0.111.0
Requires-Dist: jinja2>=3.1.0
Requires-Dist: llama-index-llms-anthropic>=0.8.4
Requires-Dist: llama-index-llms-google-genai>=0.3.0
Requires-Dist: llama-index-llms-ollama>=0.7.1
Requires-Dist: llama-index-llms-openai-like>=0.5.0
Requires-Dist: llama-index-llms-openai>=0.5.4
Requires-Dist: llama-index>=0.13.2
Requires-Dist: openai>=1.0.0
Requires-Dist: pillow>=10.0.0
Requires-Dist: posthog==6.0.2
Requires-Dist: pydantic>=2.0.0
Requires-Dist: python-dotenv>=1.0.0
Requires-Dist: requests>=2.28.0
Requires-Dist: rich>=13.0.0
Requires-Dist: typing-extensions
Requires-Dist: uvicorn[standard]>=0.30.0
Requires-Dist: websockets>=11.0.0
Provides-Extra: dev
Requires-Dist: bandit>=1.7.0; extra == 'dev'
Requires-Dist: black>=23.0.0; extra == 'dev'
Requires-Dist: mypy>=1.0.0; extra == 'dev'
Requires-Dist: ruff>=0.1.0; extra == 'dev'
Requires-Dist: safety>=2.0.0; extra == 'dev'
